azure_functions_sqs/__init__.py
azure_functions_sqs/client.py
azure_functions_sqs/message.py
azure_functions_sqs/output.py
azure_functions_sqs/trigger.py
azure_functions_sqs-1.0.0.dist-info/METADATA
azure_functions_sqs-1.0.0.dist-info/WHEEL
azure_functions_sqs-1.0.0.dist-info/RECORD
