Metadata-Version: 2.4
Name: azure-functions-sqs
Version: 1.0.0
Summary: AWS SQS bindings for Azure Functions
Project-URL: Homepage, https://github.com/laveeshb/azure-functions-sqs-extension
Project-URL: Documentation, https://github.com/laveeshb/azure-functions-sqs-extension/tree/main/python
Project-URL: Repository, https://github.com/laveeshb/azure-functions-sqs-extension
Project-URL: Issues, https://github.com/laveeshb/azure-functions-sqs-extension/issues
Author-email: Laveesh Bansal <laveeshbansal@gmail.com>
License-Expression: MIT
Keywords: aws,azure,functions,serverless,sqs
Classifier: Development Status :: 4 - Beta
Classifier: Intended Audience :: Developers
Classifier: License :: OSI Approved :: MIT License
Classifier: Operating System :: OS Independent
Classifier: Programming Language :: Python :: 3
Classifier: Programming Language :: Python :: 3.9
Classifier: Programming Language :: Python :: 3.10
Classifier: Programming Language :: Python :: 3.11
Classifier: Programming Language :: Python :: 3.12
Classifier: Topic :: Software Development :: Libraries :: Python Modules
Requires-Python: >=3.9
Requires-Dist: azure-functions>=1.17.0
Requires-Dist: boto3>=1.26.0
Provides-Extra: dev
Requires-Dist: boto3-stubs[sqs]>=1.26.0; extra == 'dev'
Requires-Dist: moto[sqs]>=4.0.0; extra == 'dev'
Requires-Dist: mypy>=1.0.0; extra == 'dev'
Requires-Dist: pytest-asyncio>=0.21.0; extra == 'dev'
Requires-Dist: pytest>=7.0.0; extra == 'dev'
Requires-Dist: ruff>=0.1.0; extra == 'dev'
